setup.cfg
setup.py
connectivipy/__init__.py
connectivipy/conn.py
connectivipy/data.py
connectivipy/mvarmodel.py
connectivipy/plot.py
connectivipy/sigific.py
connectivipy/working.py
connectivipy/wrdata.py
connectivipy.egg-info/PKG-INFO
connectivipy.egg-info/SOURCES.txt
connectivipy.egg-info/dependency_links.txt
connectivipy.egg-info/requires.txt
connectivipy.egg-info/top_level.txt
connectivipy/load/__init__.py
connectivipy/load/loaders.py
connectivipy/mvar/__init__.py
connectivipy/mvar/comp.py
connectivipy/mvar/fitting.py